{
  "startRoomId": "town_square",
  "rooms": [
    {
      "id": "town_square",
      "name": "Town Square",
      "description": "A weathered cobblestone plaza at the heart of a small town. A handsome young Labrador with mischief in his eyes notices you and wags his tail. A fountain burbles in the center, and a wooden signpost points in all directions.",
      "exits": {
        "NORTH": "tavern",
        "SOUTH": "market",
        "EAST":  "east_road",
        "WEST":  "blacksmith"
      },
      "recallBindable": true,
      "defaultRecallPoint": true,
      "itemIds": ["item_signpost", "item_fountain"],
      "npcIds": ["npc_dog_Obi", "npc_joyful_child"]
    },
    {
      "id": "tavern",
      "name": "The Rusty Flagon Tavern",
      "description": "A dimly lit tavern that smells of ale and woodsmoke. Gruff adventurers murmur at scarred oak tables. A red-faced bartender polishes mugs behind the bar.",
      "exits": {
        "SOUTH": "town_square",
        "UP":    "tavern_loft"
      },
      "itemIds": ["item_ale_mug", "item_wanted_poster"]
    },
    {
      "id": "tavern_loft",
      "name": "Tavern Loft",
      "description": "A dusty loft above the tavern. Straw mattresses are pushed against the walls. A cracked window overlooks the town square below.",
      "exits": {
        "DOWN": "tavern"
      },
      "recallBindable": true,
      "itemIds": ["item_straw_mattress", "item_cracked_window"]
    },
    {
      "id": "market",
      "name": "Town Market",
      "description": "Colourful stalls line the road – vendors hawk everything from fresh bread to peculiar trinkets. The noise and bustle is almost overwhelming.",
      "exits": {
        "NORTH": "town_square",
        "EAST":  "alchemist"
      },
      "itemIds": ["item_bread_loaf", "item_strange_trinket", "item_childs_ball"]
    },
    {
      "id": "alchemist",
      "name": "Alchemist's Shop",
      "description": "Shelves packed with bubbling vials and drying herbs crowd every surface. The air reeks of sulphur and something floral. An old alchemist peers at you over thick spectacles.",
      "exits": {
        "WEST": "market"
      },
      "itemIds": ["item_health_potion", "item_mysterious_powder"]
    },
    {
      "id": "east_road",
      "name": "East Road",
      "description": "A rutted dirt track leading away from town toward a distant dark forest. The trees loom large on the horizon. The road continues east.",
      "exits": {
        "WEST": "town_square",
        "EAST": "forest_edge"
      },
      "itemIds": []
    },
    {
      "id": "forest_edge",
      "name": "Forest Edge",
      "description": "The road dissolves into a tangle of roots and undergrowth at the edge of a dense forest. Strange sounds drift from the shadowed canopy. A narrow path leads north.",
      "exits": {
        "WEST":  "east_road",
        "NORTH": "deep_forest"
      },
      "hiddenExits": {
        "SOUTH": "cave_entrance"
      },
      "hiddenExitHints": {
        "SOUTH": "Behind a curtain of hanging vines, you discover a dark cave entrance leading <em>south</em>."
      },
      "itemIds": ["item_broken_arrow", "item_odd_mushroom"],
      "npcIds": ["npc_wounded_pilgrim"]
    },
    {
      "id": "cave_entrance",
      "name": "Cave Entrance",
      "description": "A cold draft blows from the yawning darkness ahead. The cave mouth is barely wide enough for one person. Beyond this point, the light from outside will not reach. <em>Something about this place feels draining — you sense your body will not heal naturally here.</em>",
      "exits": {
        "NORTH": "forest_edge",
        "SOUTH": "dark_passage_1"
      },
      "ambientZone": "cave",
      "suppressRegen": true,
      "itemIds": ["item_cave_moss"]
    },
    {
      "id": "dark_passage_1",
      "name": "Dark Passage",
      "description": "Pitch blackness surrounds you. The air is damp and cold. You can feel passages leading in several directions, but you cannot see which way is safe. <em>Trust your instincts... or suffer the consequences.</em>",
      "exits": {
        "NORTH": "cave_entrance",
        "SOUTH": "dark_passage_2",
        "EAST": "dark_dead_end_1",
        "WEST": "dark_dead_end_2"
      },
      "dark": true,
      "safeExit": "SOUTH",
      "wrongExitDamage": 8,
      "ambientZone": "cave",
      "suppressRegen": true,
      "itemIds": []
    },
    {
      "id": "dark_dead_end_1",
      "name": "Dark Dead End",
      "description": "You slam into a solid wall of stone. Pain shoots through your body as you stumble back.",
      "exits": {
        "WEST": "dark_passage_1"
      },
      "ambientZone": "cave",
      "suppressRegen": true,
      "itemIds": []
    },
    {
      "id": "dark_dead_end_2",
      "name": "Dark Dead End", 
      "description": "Your foot catches on a jagged rock and you crash to the ground. The fall leaves you bruised and disoriented.",
      "exits": {
        "EAST": "dark_passage_1"
      },
      "ambientZone": "cave",
      "suppressRegen": true,
      "itemIds": []
    },
    {
      "id": "dark_passage_2",
      "name": "Dark Passage",
      "description": "The darkness is absolute. Water drips somewhere nearby. You feel passages in multiple directions — a slight breeze from one suggests a way forward.",
      "exits": {
        "NORTH": "dark_passage_1",
        "SOUTH": "dark_dead_end_3",
        "EAST": "dark_passage_3",
        "WEST": "dark_dead_end_4"
      },
      "dark": true,
      "safeExit": "EAST",
      "wrongExitDamage": 8,
      "ambientZone": "cave",
      "suppressRegen": true,
      "itemIds": []
    },
    {
      "id": "dark_dead_end_3",
      "name": "Dark Dead End",
      "description": "You step into empty air and fall several feet before slamming into the ground below.",
      "exits": {
        "NORTH": "dark_passage_2"
      },
      "ambientZone": "cave",
      "suppressRegen": true,
      "itemIds": ["item_cave_moss"]
    },
    {
      "id": "dark_dead_end_4",
      "name": "Dark Dead End",
      "description": "Sharp stalactites rake across your arms as you push into a narrow crevice that goes nowhere.",
      "exits": {
        "EAST": "dark_passage_2"
      },
      "ambientZone": "cave",
      "suppressRegen": true,
      "itemIds": []
    },
    {
      "id": "dark_passage_3",
      "name": "Dark Passage",
      "description": "The stone beneath your feet is slick with moisture. You can hear the distant echo of dripping water from multiple directions.",
      "exits": {
        "WEST": "dark_passage_2",
        "NORTH": "dark_dead_end_5",
        "SOUTH": "dark_passage_4",
        "EAST": "dark_dead_end_6"
      },
      "dark": true,
      "safeExit": "SOUTH",
      "wrongExitDamage": 10,
      "ambientZone": "cave",
      "suppressRegen": true,
      "itemIds": []
    },
    {
      "id": "dark_dead_end_5",
      "name": "Dark Dead End",
      "description": "The passage narrows to nothing. You scrape against rough stone trying to force your way through.",
      "exits": {
        "SOUTH": "dark_passage_3"
      },
      "ambientZone": "cave",
      "suppressRegen": true,
      "itemIds": []
    },
    {
      "id": "dark_dead_end_6",
      "name": "Dark Dead End",
      "description": "You walk face-first into a curtain of wet, slimy moss. Spitting and wiping your face, you retreat.",
      "exits": {
        "WEST": "dark_passage_3"
      },
      "ambientZone": "cave",
      "suppressRegen": true,
      "itemIds": ["item_cave_moss"]
    },
    {
      "id": "dark_passage_4",
      "name": "Dark Passage",
      "description": "The air grows noticeably warmer here. You feel a faint updraft from somewhere below, carrying the scent of minerals.",
      "exits": {
        "NORTH": "dark_passage_3",
        "SOUTH": "dark_dead_end_7",
        "EAST": "dark_dead_end_8",
        "WEST": "dark_passage_5"
      },
      "dark": true,
      "safeExit": "WEST",
      "wrongExitDamage": 10,
      "ambientZone": "cave",
      "suppressRegen": true,
      "itemIds": []
    },
    {
      "id": "dark_dead_end_7",
      "name": "Dark Dead End",
      "description": "A sudden drop! You tumble down a rocky slope, barely managing to claw your way back up.",
      "exits": {
        "NORTH": "dark_passage_4"
      },
      "ambientZone": "cave",
      "suppressRegen": true,
      "itemIds": []
    },
    {
      "id": "dark_dead_end_8",
      "name": "Dark Dead End",
      "description": "The ceiling collapses to head height, then chest height. You crawl on your belly before realizing there's no way through.",
      "exits": {
        "WEST": "dark_passage_4"
      },
      "ambientZone": "cave",
      "suppressRegen": true,
      "itemIds": ["item_health_potion"]
    },
    {
      "id": "dark_passage_5",
      "name": "Dark Passage",
      "description": "Something feels different about this place. The darkness seems less oppressive. Is that... a faint glow ahead?",
      "exits": {
        "EAST": "dark_passage_4",
        "NORTH": "dark_dead_end_9",
        "SOUTH": "cave_heart"
      },
      "dark": true,
      "safeExit": "SOUTH",
      "wrongExitDamage": 12,
      "ambientZone": "cave",
      "suppressRegen": true,
      "itemIds": []
    },
    {
      "id": "dark_dead_end_9",
      "name": "Dark Dead End",
      "description": "You squeeze through a crack only to find yourself in a tiny chamber with no exit. The walls press in claustrophobically.",
      "exits": {
        "SOUTH": "dark_passage_5"
      },
      "ambientZone": "cave",
      "suppressRegen": true,
      "itemIds": ["item_cave_moss"]
    },
    {
      "id": "cave_heart",
      "name": "Heart of the Cave",
      "description": "A shaft of light descends from a hole high above, illuminating a small underground chamber. Crystals embedded in the walls catch the light and scatter it in rainbow hues. A sense of profound peace fills this sacred space. <em>Here, you feel your body can recover once more.</em>",
      "exits": {
        "NORTH": "dark_passage_5",
        "UP": "forest_edge"
      },
      "ambientZone": "cave",
      "itemIds": []
    },
    {
      "id": "deep_forest",
      "name": "Deep Forest",
      "description": "Huge ancient trees block out the sky. Bioluminescent fungi cast an eerie blue glow across the undergrowth. You feel watched. The path home leads south.",
      "exits": {
        "SOUTH": "forest_edge",
        "EAST": "forest_fork"
      },
      "itemIds": ["item_glowing_mushroom", "item_animal_tracks"],
      "npcIds": ["npc_lost_traveler"]
    },
    {
  "id": "forest_fork",
  "name": "Forest Fork",
  "description": "The trail divides here into two narrow paths that curl between ancient roots and mossy stones. Though the forest is silent, paw prints in the earth suggest that something loyal passed this way not long ago.",
  "exits": {
    "WEST": "deep_forest"
  },
  "hiddenExits": {
    "EAST": "old_oak_crossing"
  },
  "hiddenExitHints": {
    "EAST": "You push aside a curtain of overgrown shrubbery and discover a hidden path leading <em>east</em> — a route that clearly hasn't been used in some time."
  },
  "itemIds": ["item_pawprints", "item_mossy_stone"],
  "npcIds": ["npc_blind_guide"]
},
{
  "id": "old_oak_crossing",
  "name": "Old Oak Crossing",
  "description": "Beyond the fork, both paths join again in a hidden grove beneath an ancient oak. Sunlight spills through the leaves in golden shafts, illuminating a weathered stone at the tree's roots. A magnificent sword is embedded in the stone, and beside it sits the faint spectral form of a Labrador, tail gently thumping against the earth.",
  "exits": {
    "WEST": "forest_fork"
  },
  "itemIds": ["item_obis_oath", "item_obis_tag", "item_weathered_stone", "item_ancient_oak"],
  "npcIds": ["npc_keeper_of_the_bond"]
},
    {
      "id": "blacksmith",
      "name": "Blacksmith's Forge",
      "description": "The heat from the forge is intense. Weapons and armour hang from every hook. A massive blacksmith hammers a glowing sword blade on a thick anvil. A wooden gate to the west leads to the training yard.",
      "exits": {
        "EAST": "town_square",
        "WEST": "training_yard"
      },
      "itemIds": ["item_iron_sword", "item_leather_shield", "item_anvil"]
    },
    {
      "id": "training_yard",
      "name": "Training Yard",
      "description": "A dusty courtyard enclosed by wooden fencing, clearly used for martial practice. Straw-stuffed training dummies stand at attention in a row, their burlap faces scarred from countless strikes. Weapon racks line the perimeter, and a grizzled instructor watches over the area with a critical eye.",
      "exits": {
        "EAST": "blacksmith"
      },
      "itemIds": ["item_weapon_rack", "item_practice_sword", "item_training_target"],
      "npcIds": ["npc_training_dummy_1", "npc_training_dummy_2", "npc_training_dummy_3", "npc_drill_instructor"]
    }
  ]
}
